niftiprocessing/__init__.py
niftiprocessing/__main__.py
niftiprocessing/graphical.py
niftiprocessing/nifti.py
niftiprocessing/niftihelper.py
niftiprocessing/numpyhelper.py
niftiprocessing/preprocessing.py
niftiprocessing-0.0.5.dist-info/LICENSE
niftiprocessing-0.0.5.dist-info/METADATA
niftiprocessing-0.0.5.dist-info/WHEEL
niftiprocessing-0.0.5.dist-info/entry_points.txt
niftiprocessing-0.0.5.dist-info/top_level.txt
niftiprocessing-0.0.5.dist-info/RECORD
