Metadata-Version: 2.1
Name: niftiprocessing
Version: 0.0.5
Summary: A nifti processing tool
Home-page: https://github.com/alleetw101/niftiprocessing
Author: Alan Lee
Author-email: alleetw101@gmail.com
License: UNKNOWN
Platform: UNKNOWN
Classifier: Programming Language :: Python :: 3
Classifier: License :: OSI Approved :: MIT License
Classifier: Operating System :: OS Independent
Requires-Python: >=3.6
Requires-Dist: SimpleITK (>=2.0)
Requires-Dist: numpy (>=1.0)
